Metadata-Version: 2.1
Name: matFik
Version: 0.0.2
Summary: Matrix Function
Home-page: 
Author: Fikri Kamaluddin
Author-email: fikrikamaluddin07@gmail.com
License: MIT
Keywords: matrix
License-File: LICENCE.txt
